setup.py
cloudeebus/__init__.py
cloudeebus/cloudeebus.py
cloudeebus.egg-info/PKG-INFO
cloudeebus.egg-info/SOURCES.txt
cloudeebus.egg-info/dependency_links.txt
cloudeebus.egg-info/requires.txt
cloudeebus.egg-info/top_level.txt