Metadata-Version: 1.1
Name: cloudeebus
Version: 0.6.0
Summary: Javascript-DBus bridge
Home-page: https://github.com/01org/cloudeebus/wiki
Author: Luc Yriarte, Christophe Guiraud, Frederic Paut
Author-email: luc.yriarte@intel.com, christophe.guiraud@intel.com, frederic.paut@intel.com
License: http://www.apache.org/licenses/LICENSE-2.0
Keywords: cloudeebus autobahn websocket dbus javascript bridge
Platform: Any
Classifier: License :: OSI Approved :: Apache Software License
Classifier: Development Status :: 3 - Alpha
Classifier: Environment :: Console
Classifier: Intended Audience :: Developers
Classifier: Operating System :: OS Independent
Classifier: Programming Language :: Python
Classifier: Topic :: Internet
Classifier: Topic :: Software Development :: Libraries
